DAC43608/__init__.py
DAC43608/py.typed
DAC43608-0.2.7.dist-info/LICENSE
DAC43608-0.2.7.dist-info/METADATA
DAC43608-0.2.7.dist-info/WHEEL
DAC43608-0.2.7.dist-info/top_level.txt
DAC43608-0.2.7.dist-info/RECORD
