Metadata-Version: 2.1
Name: DAC43608
Version: 0.2.7
Summary: A python wrapper for interacting with the DAC43608
Home-page: https://github.com/Pioreactor/DAC43608
Author: Cam Davidson-Pilon
Author-email: cam@pioreactor.com
License: MIT
Platform: UNKNOWN
Requires-Python: >=3.6
License-File: LICENSE
Requires-Dist: adafruit-circuitpython-busdevice
Requires-Dist: Adafruit-Blinka
